claif_gem/__init__.py
claif_gem/__version__.py
claif_gem/cli.py
claif_gem/client.py
claif_gem-1.0.30.dist-info/METADATA
claif_gem-1.0.30.dist-info/WHEEL
claif_gem-1.0.30.dist-info/entry_points.txt
claif_gem-1.0.30.dist-info/licenses/LICENSE
claif_gem-1.0.30.dist-info/RECORD
